prvd/__init__.py
prvd/api_client.py
prvd/goldmine.py
prvd/ident.py
prvd/message_bus.py
prvd-0.2.1.dist-info/LICENSE
prvd-0.2.1.dist-info/METADATA
prvd-0.2.1.dist-info/WHEEL
prvd-0.2.1.dist-info/top_level.txt
prvd-0.2.1.dist-info/RECORD
