Metadata-Version: 2.1
Name: prvd
Version: 0.2.1
Summary: Provide python client
Home-page: https://github.com/provideservices/provide-python
Author: Kyle Thomas
Author-email: kyle@provide.services
License: UNKNOWN
Platform: UNKNOWN
Requires-Dist: ipfshttpclient
Requires-Dist: pyjwt
Requires-Dist: requests
